MANIFEST.in
README.md
setup.py
ropchain/__init__.py
ropchain/emulator.py
ropchain/register.py
ropchain/test.py
ropchain/wrapper.py
ropchain.egg-info/PKG-INFO
ropchain.egg-info/SOURCES.txt
ropchain.egg-info/dependency_links.txt
ropchain.egg-info/top_level.txt
ropchain/ffi/waf
ropchain/ffi/wscript
ropchain/ffi/src/common/builder.cpp
ropchain/ffi/src/common/builder.h
ropchain/ffi/src/common/config.cpp
ropchain/ffi/src/common/config.h
ropchain/ffi/src/common/emulator.cpp
ropchain/ffi/src/common/emulator.h
ropchain/ffi/src/common/gadget.cpp
ropchain/ffi/src/common/gadget.h
ropchain/ffi/src/common/insn.cpp
ropchain/ffi/src/common/insn.h
ropchain/ffi/src/common/regs.cpp
ropchain/ffi/src/common/regs.h
ropchain/ffi/src/common/ropchain.cpp
ropchain/ffi/src/common/ropchain.h
ropchain/ffi/src/common/solver.cpp
ropchain/ffi/src/common/solver.h
ropchain/ffi/src/common/util.cpp
ropchain/ffi/src/common/util.h
ropchain/ffi/src/common/asm/add.cpp
ropchain/ffi/src/common/asm/add.h
ropchain/ffi/src/common/asm/and.cpp
ropchain/ffi/src/common/asm/and.h
ropchain/ffi/src/common/asm/dec.cpp
ropchain/ffi/src/common/asm/dec.h
ropchain/ffi/src/common/asm/inc.cpp
ropchain/ffi/src/common/asm/inc.h
ropchain/ffi/src/common/asm/lea.cpp
ropchain/ffi/src/common/asm/lea.h
ropchain/ffi/src/common/asm/mov.cpp
ropchain/ffi/src/common/asm/mov.h
ropchain/ffi/src/common/asm/movzx.cpp
ropchain/ffi/src/common/asm/movzx.h
ropchain/ffi/src/common/asm/neg.cpp
ropchain/ffi/src/common/asm/neg.h
ropchain/ffi/src/common/asm/or.cpp
ropchain/ffi/src/common/asm/or.h
ropchain/ffi/src/common/asm/pop.cpp
ropchain/ffi/src/common/asm/pop.h
ropchain/ffi/src/common/asm/shl.cpp
ropchain/ffi/src/common/asm/shl.h
ropchain/ffi/src/common/asm/xchg.cpp
ropchain/ffi/src/common/asm/xchg.h
ropchain/ffi/src/common/asm/xor.cpp
ropchain/ffi/src/common/asm/xor.h
ropchain/ffi/src/common/frontend/r2/r2_loader.cpp
ropchain/ffi/src/common/frontend/r2/r2_loader.h
ropchain/ffi/src/common/frontend/rp++/rp_loader.cpp
ropchain/ffi/src/common/frontend/rp++/rp_loader.h
ropchain/ffi/src/common/middle/middle.cpp
ropchain/ffi/src/common/middle/middle.h
