Metadata-Version: 1.0
Name: ropchain
Version: 0.1.9.4
Summary: ROPChain generator
Home-page: https://github.com/kriw/ropchain
Author: kriw
Author-email: kotarou777775@gmail.com
License: GPL3.0
Platform: UNKNOWN
